enhaaancedQueues.py
enhaaancedQueues-0.7.dist-info/LICENSE
enhaaancedQueues-0.7.dist-info/METADATA
enhaaancedQueues-0.7.dist-info/WHEEL
enhaaancedQueues-0.7.dist-info/top_level.txt
enhaaancedQueues-0.7.dist-info/RECORD
